LICENSE
MANIFEST.in
README.md
requirements.txt
setup.py
cloudhealth/__init__.py
cloudhealth_fluent.egg-info/PKG-INFO
cloudhealth_fluent.egg-info/SOURCES.txt
cloudhealth_fluent.egg-info/dependency_links.txt
cloudhealth_fluent.egg-info/requires.txt
cloudhealth_fluent.egg-info/top_level.txt