Metadata-Version: 1.1
Name: cloudhealth-fluent
Version: 0.0.11
Summary: CloudHealth fluent interface
Home-page: https://github.com/awslabs/cloudhealth-fluent
Author: troylar
Author-email: troylar@pm.me
License: Apache-2.0
Keywords: cloudhealth
Platform: UNKNOWN
Classifier: Development Status :: 5 - Production/Stable
Classifier: Topic :: Utilities
Classifier: License :: OSI Approved :: Apache Software License
